jtak/__init__.py
jtak/__version__.py
jtak/chat.py
jtak/client.py
jtak/cot.py
jtak/state.py
jtak/user.py
jtak/takproto/README.md
jtak/takproto/ThirdPartyLicense.md
jtak/takproto/__init__.py
jtak/takproto/common.py
jtak/takproto/messages/__init__.py
jtak/takproto/messages/contact_pb2.py
jtak/takproto/messages/contact_pb2.pyi
jtak/takproto/messages/cotevent_pb2.py
jtak/takproto/messages/cotevent_pb2.pyi
jtak/takproto/messages/detail_pb2.py
jtak/takproto/messages/detail_pb2.pyi
jtak/takproto/messages/group_pb2.py
jtak/takproto/messages/group_pb2.pyi
jtak/takproto/messages/precisionlocation_pb2.py
jtak/takproto/messages/precisionlocation_pb2.pyi
jtak/takproto/messages/status_pb2.py
jtak/takproto/messages/status_pb2.pyi
jtak/takproto/messages/takcontrol_pb2.py
jtak/takproto/messages/takcontrol_pb2.pyi
jtak/takproto/messages/takmessage_pb2.py
jtak/takproto/messages/takmessage_pb2.pyi
jtak/takproto/messages/takv_pb2.py
jtak/takproto/messages/takv_pb2.pyi
jtak/takproto/messages/track_pb2.py
jtak/takproto/messages/track_pb2.pyi
jtak/workers/__init__.py
jtak/workers/conf.py
jtak/workers/direct_worker.py
jtak/workers/mesh_worker.py
jtak/workers/stream_worker.py
jtak/workers/tak_worker.py
jtak/workers/io/__init__.py
jtak/workers/io/net.py
jtak/workers/io/tcp.py
jtak/workers/io/udp.py
jtak_example.py
jtak-1.0.5.dist-info/METADATA
jtak-1.0.5.dist-info/WHEEL
jtak-1.0.5.dist-info/entry_points.txt
jtak-1.0.5.dist-info/licenses/LICENSE.md
jtak-1.0.5.dist-info/RECORD
