Metadata-Version: 2.4
Name: jtak
Version: 1.0.5
Summary: TAK client
Project-URL: Repository, https://github.com/cmu-sei/jtak
Project-URL: Issues, https://github.com/cmu-sei/jtak/issues
Author-email: Jeff Mattson <jmattson@sei.cmu.edu>
License: jtak
License-File: LICENSE.md
Keywords: ATAK,CoT,Cursor on Target,TAK
Classifier: Development Status :: 5 - Production/Stable
Classifier: Operating System :: OS Independent
Classifier: Programming Language :: Python
Classifier: Programming Language :: Python :: 3.10
Classifier: Programming Language :: Python :: 3.11
Classifier: Programming Language :: Python :: 3.12
Requires-Python: <4,>=3.10
Requires-Dist: asyncio-dgram
Requires-Dist: cryptography
Requires-Dist: delimited-protobuf
Requires-Dist: protobuf
Requires-Dist: psutil
